{
  "totalPages": 1,
  "pages": [
    {
      "page": 1,
      "size": 20,
      "hasNextPage": false,
      "hasPreviousPage": false,
      "result": [
        {
          "bookingCode": "bw2e9451ec",
          "accountId": "701122ca-e6da-ee11-8176-00155da61415",
          "referenceId": "cefb106d-5992-4d9f-984c-63ce2e3c3bfd",
          "currencyCode": "ZAR",
          "createdDate": "2026-01-02T08:03:18.773",
          "activeUntilDate": "2027-01-02T08:03:18.613",
          "cumulativeWagerAmount": 1,
          "amountEarned": 0.04,
          "amountPaid": 0,
          "lastPayoutDate": "2026-01-02T08:03:18.773",
          "timesUsed": 1,
          "lastPayoutTimesUsedStamp": 0,
          "id": "10dd7877-bd4c-4923-ba4b-41c641606ea7",
          "editedById": "00000000-0000-0000-0000-000000000000",
          "editedDateTime": "0001-01-01T00:00:00",
          "isDeleted": false,
          "version": 0
        },
        {
          "bookingCode": "bw2e93c10d",
          "accountId": "701122ca-e6da-ee11-8176-00155da61415",
          "referenceId": "2af1ee52-3f8d-4307-8e5c-8582fc9e6f0e",
          "currencyCode": "ZAR",
          "createdDate": "2026-01-02T08:03:43.783",
          "activeUntilDate": "2027-01-02T08:03:43.807",
          "cumulativeWagerAmount": 1,
          "amountEarned": 0.04,
          "amountPaid": 0,
          "lastPayoutDate": "2026-01-02T08:03:43.783",
          "timesUsed": 1,
          "lastPayoutTimesUsedStamp": 0,
          "id": "4ac6ba18-7363-454a-af35-18c19ad17d9e",
          "editedById": "00000000-0000-0000-0000-000000000000",
          "editedDateTime": "0001-01-01T00:00:00",
          "isDeleted": false,
          "version": 0
        },
        {
          "bookingCode": "BW2F9FA786",
          "accountId": "701122ca-e6da-ee11-8176-00155da61415",
          "referenceId": "9878af8e-2bce-44ad-bb21-b2fa7ee41076",
          "currencyCode": "ZAR",
          "createdDate": "2026-01-05T11:39:47.953",
          "activeUntilDate": "2027-01-05T11:39:47.97",
          "cumulativeWagerAmount": 1,
          "amountEarned": 0.04,
          "amountPaid": 0,
          "lastPayoutDate": "2026-01-05T11:39:47.953",
          "timesUsed": 1,
          "lastPayoutTimesUsedStamp": 0,
          "id": "c4bb39ce-cf97-4a04-ba20-ef6873f7f5c0",
          "editedById": "00000000-0000-0000-0000-000000000000",
          "editedDateTime": "0001-01-01T00:00:00",
          "isDeleted": false,
          "version": 0
        },
        {
          "bookingCode": "bw2fce9330",
          "accountId": "701122ca-e6da-ee11-8176-00155da61415",
          "referenceId": "c5ac8035-ab8b-4bee-a2d1-b00f4022a54d",
          "currencyCode": "ZAR",
          "createdDate": "2026-01-06T07:58:14.06",
          "activeUntilDate": "2027-01-06T07:58:13.957",
          "cumulativeWagerAmount": 5,
          "amountEarned": 0.2,
          "amountPaid": 0,
          "lastPayoutDate": "2026-01-06T07:58:14.06",
          "timesUsed": 1,
          "lastPayoutTimesUsedStamp": 0,
          "id": "011ce84e-1696-4c62-99ef-c4474a5649ac",
          "editedById": "00000000-0000-0000-0000-000000000000",
          "editedDateTime": "0001-01-01T00:00:00",
          "isDeleted": false,
          "version": 0
        },
        {
          "bookingCode": "bw2fcfada5",
          "accountId": "701122ca-e6da-ee11-8176-00155da61415",
          "referenceId": "7ea50473-3495-4885-8b32-b12ce822eb1e",
          "currencyCode": "ZAR",
          "createdDate": "2026-01-06T08:02:46.803",
          "activeUntilDate": "2027-01-06T08:02:46.84",
          "cumulativeWagerAmount": 5,
          "amountEarned": 0.2,
          "amountPaid": 0,
          "lastPayoutDate": "2026-01-06T08:02:46.803",
          "timesUsed": 1,
          "lastPayoutTimesUsedStamp": 0,
          "id": "d03c9ea6-4abb-4b06-9e03-bba2e911cde5",
          "editedById": "00000000-0000-0000-0000-000000000000",
          "editedDateTime": "0001-01-01T00:00:00",
          "isDeleted": false,
          "version": 0
        }
      ]
    }
  ]
}